[{
  "totalCertifications": 318,
  "fieldOfStudy": "Arts",
  "educationLevel": "PhD"
},
{
  "totalCertifications": 314,
  "fieldOfStudy": "Medicine",
  "educationLevel": "High School"
},
{
  "totalCertifications": 310,
  "fieldOfStudy": "Biology",
  "educationLevel": "High School"
},
{
  "totalCertifications": 309,
  "fieldOfStudy": "Medicine",
  "educationLevel": "Bachelor's"
},
{
  "totalCertifications": 309,
  "fieldOfStudy": "Education",
  "educationLevel": "High School"
},
{
  "totalCertifications": 307,
  "fieldOfStudy": "Education",
  "educationLevel": "Master's"
},
{
  "totalCertifications": 307,
  "fieldOfStudy": "Medicine",
  "educationLevel": "PhD"
},
{
  "totalCertifications": 305,
  "fieldOfStudy": "Economics",
  "educationLevel": "Master's"
},
{
  "totalCertifications": 302,
  "fieldOfStudy": "Law",
  "educationLevel": "Master's"
},
{
  "totalCertifications": 302,
  "fieldOfStudy": "Business",
  "educationLevel": "Master's"
},
{
  "totalCertifications": 300,
  "fieldOfStudy": "Education",
  "educationLevel": "PhD"
},
{
  "totalCertifications": 299,
  "fieldOfStudy": "Biology",
  "educationLevel": "PhD"
},
{
  "totalCertifications": 296,
  "fieldOfStudy": "Economics",
  "educationLevel": "High School"
},
{
  "totalCertifications": 296,
  "fieldOfStudy": "Education",
  "educationLevel": "Bachelor's"
},
{
  "totalCertifications": 294,
  "fieldOfStudy": "Law",
  "educationLevel": "High School"
},
{
  "totalCertifications": 293,
  "fieldOfStudy": "Law",
  "educationLevel": "Bachelor's"
},
{
  "totalCertifications": 292,
  "fieldOfStudy": "Biology",
  "educationLevel": "Master's"
},
{
  "totalCertifications": 292,
  "fieldOfStudy": "Business",
  "educationLevel": "High School"
},
{
  "totalCertifications": 291,
  "fieldOfStudy": "Business",
  "educationLevel": "PhD"
},
{
  "totalCertifications": 291,
  "fieldOfStudy": "Arts",
  "educationLevel": "Master's"
},
{
  "totalCertifications": 290,
  "fieldOfStudy": "Business",
  "educationLevel": "Bachelor's"
},
{
  "totalCertifications": 290,
  "fieldOfStudy": "Computer Science",
  "educationLevel": "Bachelor's"
},
{
  "totalCertifications": 288,
  "fieldOfStudy": "Mechanical Engineering",
  "educationLevel": "PhD"
},
{
  "totalCertifications": 288,
  "fieldOfStudy": "Psychology",
  "educationLevel": "PhD"
},
{
  "totalCertifications": 285,
  "fieldOfStudy": "Arts",
  "educationLevel": "High School"
},
{
  "totalCertifications": 283,
  "fieldOfStudy": "Computer Science",
  "educationLevel": "PhD"
},
{
  "totalCertifications": 279,
  "fieldOfStudy": "Economics",
  "educationLevel": "PhD"
},
{
  "totalCertifications": 277,
  "fieldOfStudy": "Mechanical Engineering",
  "educationLevel": "Bachelor's"
},
{
  "totalCertifications": 276,
  "fieldOfStudy": "Psychology",
  "educationLevel": "Master's"
},
{
  "totalCertifications": 276,
  "fieldOfStudy": "Psychology",
  "educationLevel": "High School"
},
{
  "totalCertifications": 274,
  "fieldOfStudy": "Biology",
  "educationLevel": "Bachelor's"
},
{
  "totalCertifications": 273,
  "fieldOfStudy": "Law",
  "educationLevel": "PhD"
},
{
  "totalCertifications": 271,
  "fieldOfStudy": "Mechanical Engineering",
  "educationLevel": "High School"
},
{
  "totalCertifications": 271,
  "fieldOfStudy": "Mechanical Engineering",
  "educationLevel": "Master's"
},
{
  "totalCertifications": 264,
  "fieldOfStudy": "Medicine",
  "educationLevel": "Master's"
},
{
  "totalCertifications": 264,
  "fieldOfStudy": "Computer Science",
  "educationLevel": "Master's"
},
{
  "totalCertifications": 256,
  "fieldOfStudy": "Psychology",
  "educationLevel": "Bachelor's"
},
{
  "totalCertifications": 254,
  "fieldOfStudy": "Economics",
  "educationLevel": "Bachelor's"
},
{
  "totalCertifications": 247,
  "fieldOfStudy": "Computer Science",
  "educationLevel": "High School"
},
{
  "totalCertifications": 246,
  "fieldOfStudy": "Arts",
  "educationLevel": "Bachelor's"
},
{
  "totalCertifications": 0,
  "fieldOfStudy": null,
  "educationLevel": null
}]